README.md
setup.py
openbsd/__init__.py
openbsd/openbsd_builder.py
openbsd.egg-info/PKG-INFO
openbsd.egg-info/SOURCES.txt
openbsd.egg-info/dependency_links.txt
openbsd.egg-info/requires.txt
openbsd.egg-info/top_level.txt