Metadata-Version: 2.1
Name: openbsd
Version: 0.1.0
Summary: OpenBSD Library
Home-page: UNKNOWN
Author: Yuce Tekol
Author-email: yucetekol@gmail.com
License: BSD
Download-URL: https://github.com/yuce/pyopenbsd
Keywords: OpenBSD
Platform: UNKNOWN
Classifier: Development Status :: 3 - Alpha
Classifier: Intended Audience :: Developers
Classifier: Programming Language :: Python :: 2
Classifier: Programming Language :: Python :: 2.7
Classifier: Programming Language :: Python :: 3
Classifier: Programming Language :: Python :: 3.6
Classifier: Operating System :: POSIX :: BSD :: OpenBSD
Classifier: License :: OSI Approved :: BSD License
